CHANGES.txt
MANIFEST.in
README.rst
RELEASE-VERSION
gitversion.py
setup.py
daqflex/__init__.py
daqflex/devices.py
daqflex/utils.py
daqflex/firmware/USB_1608G.rbf
pydaqflex.egg-info/PKG-INFO
pydaqflex.egg-info/SOURCES.txt
pydaqflex.egg-info/dependency_links.txt
pydaqflex.egg-info/requires.txt
pydaqflex.egg-info/top_level.txt