Metadata-Version: 1.1
Name: pydaqflex
Version: 0.2.3
Summary: Python port of the Measurement Computing DAQFlex framework
Home-page: https://github.com/torfbolt/PyDAQFlex
Author: David Kiliani
Author-email: mail@davidkiliani.de
License: BSD
Keywords: mmc daqflex measurement computing usb driver
Platform: UNKNOWN
Classifier: License :: OSI Approved :: BSD License
Classifier: Programming Language :: Python
Classifier: Programming Language :: Python :: 3
Classifier: Operating System :: OS Independent
Classifier: Development Status :: 3 - Alpha
Classifier: Intended Audience :: Developers
Classifier: Intended Audience :: Science/Research
Classifier: Topic :: Scientific/Engineering
Classifier: Topic :: System :: Hardware :: Hardware Drivers
Classifier: Topic :: Software Development :: Libraries :: Python Modules
